pytestdornech/CHANGELOG.md
pytestdornech/__init__.py
pytestdornech/_version.py
pytestdornech/skeleton.py
pytestdornech-1.0.0.dist-info/METADATA
pytestdornech-1.0.0.dist-info/WHEEL
pytestdornech-1.0.0.dist-info/entry_points.txt
pytestdornech-1.0.0.dist-info/licenses/AUTHORS.md
pytestdornech-1.0.0.dist-info/licenses/LICENSE.txt
pytestdornech-1.0.0.dist-info/RECORD
