Metadata-Version: 2.4
Name: pytestdornech
Version: 1.0.0
Summary: Dornech's testpackage
Project-URL: Documentation, https://dornech.github.io/pytestdornech
Project-URL: Source, https://github.com/dornech/pytestdornech
Project-URL: Tracker, https://github.com/dornech/pytestdornech/issues
Project-URL: Sponsor, https://github.com/sponsors/dornech
Author-email: dornech <dornech@gmx.de>
License: MIT
License-File: AUTHORS.md
License-File: LICENSE.txt
Keywords: keyword_1,keyword_2
Classifier: Development Status :: 2 - Pre-Alpha
Classifier: Programming Language :: Python
Classifier: Programming Language :: Python :: 3.9
Classifier: Programming Language :: Python :: 3.10
Classifier: Programming Language :: Python :: 3.11
Classifier: Programming Language :: Python :: 3.12
Classifier: Programming Language :: Python :: 3.13
Classifier: Programming Language :: Python :: Implementation :: CPython
Requires-Python: >=3.9
Requires-Dist: typer
